Workbook

Sheet Cover
B2: Apple Inc. (AAPL) Financial Model & DCF Valuation
B8: 5-Year Historical Analysis | 5-Year Projection | DCF Valuation | Trading Comps
B10: Company | E10: Apple Inc.
B11: Ticker | E11: AAPL
B12: Exchange | E12: NASDAQ
B13: Sector | E13: Technology
B14: Industry | E14: Consumer Electronics / Software
B15: Currency | E15: USD (in $millions unless noted)
B16: Fiscal Year End | E16: September 30
B17: Historical Period | E17: FY2019 – FY2023
B18: Projection Period | E18: FY2024E – FY2028E
B19: Share Price (Ref.) | E19: $195.00
B20: Shares Outstanding | E20: 15,441M
B21: Market Cap (Ref.) | E21: $3,011B
B23: 📋 Workbook Navigation
B24: Assumptions | E24: Key model drivers: growth rates, margins, WACC components
B25: Income Statement | E25: P&L — 5 years historical + 5 years projected
B26: Balance Sheet | E26: Assets, liabilities, equity — historical + projected
B27: Cash Flow | E27: Operating / Investing / Financing — FCF build
B28: DCF Valuation | E28: WACC, terminal value, intrinsic value per share
B29: Trading Comps | E29: Peer benchmarking — EV/Revenue, EV/EBITDA, P/E
B30: Sensitivity Analysis | E30: WACC × Growth rate matrix — price range

Sheet Assumptions
A1: Key Model Assumptions — Apple Inc. (AAPL)
A3: INCOME STATEMENT DRIVERS
A4: Assumption | B4: Definition / Notes | C4: FY2024E | D4: FY2025E | E4: FY2026E | F4: FY2027E | G4: FY2028E
A5: Revenue Growth Rate | B5: YoY % change in total revenue | C5: 0.043 | D5: 0.07 | E5: 0.08 | F5: 0.075 | G5: 0.065
A6: Gross Profit Margin | B6: Gross profit as % of revenue | C6: 0.443 | D6: 0.448 | E6: 0.452 | F6: 0.455 | G6: 0.455
A7: R&D Expense % Rev. | B7: R&D as % of revenue | C7: 0.079 | D7: 0.078 | E7: 0.077 | F7: 0.076 | G7: 0.075
A8: SG&A Expense % Rev. | B8: SG&A as % of revenue | C8: 0.064 | D8: 0.063 | E8: 0.062 | F8: 0.061 | G8: 0.06
A9: Effective Tax Rate | B9: Income tax as % of pre-tax income | C9: 0.155 | D9: 0.155 | E9: 0.155 | F9: 0.155 | G9: 0.155
A10: D&A % Revenue | B10: Depreciation & Amortization | C10: 0.03 | D10: 0.029 | E10: 0.028 | F10: 0.027 | G10: 0.026
A13: BALANCE SHEET & CASH FLOW DRIVERS
A14: Assumption | B14: Definition / Notes | C14: FY2024E | D14: FY2025E | E14: FY2026E | F14: FY2027E | G14: FY2028E
A15: CapEx % Revenue | B15: Capital expenditures / Revenue | C15: 0.029 | D15: 0.028 | E15: 0.028 | F15: 0.027 | G15: 0.026
A16: NWC % Revenue | B16: Net Working Capital / Revenue | C16: 0.045 | D16: 0.045 | E16: 0.045 | F16: 0.045 | G16: 0.045
A17: AR Days | B17: Accounts Receivable days outstanding | C17: 28 | D17: 28 | E17: 27 | F17: 27 | G17: 27
A18: Inventory Days | B18: Inventory days on hand | C18: 6 | D18: 6 | E18: 6 | F18: 6 | G18: 5
A19: AP Days | B19: Accounts Payable days outstanding | C19: 59 | D19: 58 | E19: 57 | F19: 56 | G19: 55
A22: WACC COMPONENTS
A23: Component | B23: Notes | C23: Value
A24: Risk-Free Rate | B24: 10-year US Treasury yield (as of model date) | C24: 0.0425
A25: Equity Risk Premium | B25: Historical ERP — Damodaran estimate | C25: 0.055
A26: Beta (Levered) | B26: 5-year monthly vs S&P 500; source: Bloomberg | C26: 1.25
A27: Cost of Equity (CAPM) | B27: ≈rf + β × ERP | C27: =C24+C26*C25 -> 0.11125
A28: Pre-Tax Cost of Debt | B28: Weighted avg yield on outstanding bonds | C28: 0.048
A29: Tax Rate | B29: Effective tax rate from income statement | C29: 0.155
A30: After-Tax Cost of Debt | B30: ≈kd × (1 – Tax Rate) | C30: =C28*(1-C29) -> 0.04056
A31: Equity Weight | B31: Market cap / (Market cap + Debt) | C31: 0.92
A32: Debt Weight | B32: Debt / (Market cap + Debt) | C32: 0.08
A33: WACC | B33: ≈ke×We + Kd×Wd | C33: =C27*C31+C30*C32 -> 0.1055948
A37: COLOR LEGEND
A38: ■ Yellow background = Hardcoded input — user can change
A39: ■ Blue text = Hardcoded number (input assumption)
A40: ■ Black text = Calculated formula
A41: ■ Blue-grey fill = Total / WACC output
A42: ■ Green text = Cross-sheet link

Sheet Income Statement
A1: Income Statement — Apple Inc. (AAPL) | $ in Millions
B2: FY2019 | C2: FY2020 | D2: FY2021 | E2: FY2022 | F2: FY2023 | G2: FY2024E | H2: FY2025E | I2: FY2026E | J2: FY2027E | K2: FY2028E
B3: ◄ Historical ► | G3: ◄ Projected (Estimated) ►
A4: REVENUE
A5: Revenue | B5: 260174 | C5: 274515 | D5: 365817 | E5: 394328 | F5: 383285 | G5: =F5*(1+Assumptions!C5) -> 399766.26 | H5: =G5*(1+Assumptions!D5) -> 427749.89 | I5: =H5*(1+Assumptions!E5) -> 461969.88 | J5: =I5*(1+Assumptions!F5) -> 496617.63 | K5: =J5*(1+Assumptions!G5) -> 528897.77
A7: COST OF GOODS SOLD
A8: Cost of Revenue | B8: 161782 | C8: 169559 | D8: 212981 | E8: 223546 | F8: 214137 | G8: =G5*(1-Assumptions!C6) -> 222669.8 | H8: =H5*(1-Assumptions!D6) -> 236117.94 | I8: =I5*(1-Assumptions!E6) -> 253159.5 | J8: =J5*(1-Assumptions!F6) -> 270656.61 | K8: =K5*(1-Assumptions!G6) -> 288249.29
A9: Gross Profit | B9: 98392 | C9: 104956 | D9: 152836 | E9: 170782 | F9: 169148 | G9: =G5-G8 -> 177096.45 | H9: =H5-H8 -> 191631.95 | I9: =I5-I8 -> 208810.39 | J9: =J5-J8 -> 225961.02 | K9: =K5-K8 -> 240648.49
A10: Gross Margin % | B10: =B9/B5 -> 0.37817768 | C10: =C9/C5 -> 0.38233248 | D10: =D9/D5 -> 0.4177936 | E10: =E9/E5 -> 0.43309631 | F10: =F9/F5 -> 0.4413113 | G10: =G9/G5 -> 0.443 | H10: =H9/H5 -> 0.448 | I10: =I9/I5 -> 0.452 | ... K10: =K9/K5 -> 0.455
A12: OPERATING EXPENSES
A13: R&D Expense | B13: 16217 | C13: 18752 | D13: 21914 | E13: 26251 | F13: 29915 | G13: =G5*Assumptions!C7 -> 31581.534 | H13: =H5*Assumptions!D7 -> 33364.492 | I13: =I5*Assumptions!E7 -> 35571.681 | J13: =J5*Assumptions!F7 -> 37742.94 | K13: =K5*Assumptions!G7 -> 39667.333
A14: SG&A Expense | B14: 18245 | C14: 19916 | D14: 21973 | E14: 25094 | F14: 24932 | G14: =G5*Assumptions!C8 -> 25585.04 | H14: =H5*Assumptions!D8 -> 26948.243 | I14: =I5*Assumptions!E8 -> 28642.133 | J14: =J5*Assumptions!F8 -> 30293.675 | K14: =K5*Assumptions!G8 -> 31733.866
A15: Total OpEx | B15: 34462 | C15: 38668 | D15: 43887 | E15: 51345 | F15: 54847 | G15: =G13+G14 -> 57166.574 | H15: =H13+H14 -> 60312.735 | I15: =I13+I14 -> 64213.814 | J15: =J13+J14 -> 68036.615 | K15: =K13+K14 -> 71401.199
A16: Operating Income (EBIT) | B16: 63930 | C16: 66288 | D16: 108949 | E16: 119437 | F16: 114301 | G16: =G9-G15 -> 119929.88 | H16: =H9-H15 -> 131319.22 | I16: =I9-I15 -> 144596.57 | J16: =J9-J15 -> 157924.4 | K16: =K9-K15 -> 169247.29
A17: EBIT Margin % | B17: =B16/B5 -> 0.24572017 | C17: =C16/C5 -> 0.24147314 | D17: =D16/D5 -> 0.29782378 | E17: =E16/E5 -> 0.30288744 | F17: =F16/F5 -> 0.29821412 | G17: =G16/G5 -> 0.3 | H17: =H16/H5 -> 0.307 | I17: =I16/I5 -> 0.313 | ... K17: =K16/K5 -> 0.32
A19: BELOW THE LINE
A20: Interest & Other Income | B20: 500 | C20: 500 | D20: 500 | E20: 500 | F20: 500 | G20: 500 | H20: 500 | I20: 500 | J20: 500 | K20: 500
A21: Pre-Tax Income (EBT) | B21: 64430 | C21: 66788 | D21: 109449 | E21: 119937 | F21: 114801 | G21: =G16+G20 -> 120429.88 | H21: =H16+H20 -> 131819.22 | I21: =I16+I20 -> 145096.57 | J21: =J16+J20 -> 158424.4 | K21: =K16+K20 -> 169747.29
A22: Income Tax Expense | B22: 9987 | C22: 10352 | D22: 16965 | E22: 18590 | F22: 17794 | G22: =G21*Assumptions!C9 -> 18666.631 | H22: =H21*Assumptions!D9 -> 20431.979 | I22: =I21*Assumptions!E9 -> 22489.969 | J22: =J21*Assumptions!F9 -> 24555.783 | K22: =K21*Assumptions!G9 -> 26310.829
A23: Net Income | B23: 55256 | C23: 57411 | D23: 94680 | E23: 99803 | F23: 96995 | G23: =G21-G22 -> 101763.25 | H23: =H21-H22 -> 111387.24 | I23: =I21-I22 -> 122606.6 | J23: =J21-J22 -> 133868.62 | K23: =K21-K22 -> 143436.46
A24: Net Margin % | B24: =B23/B5 -> 0.21238095 | C24: =C23/C5 -> 0.20913611 | D24: =D23/D5 -> 0.25881793 | E24: =E23/E5 -> 0.25309641 | F24: =F23/F5 -> 0.25306234 | G24: =G23/G5 -> 0.25455687 | H24: =H23/H5 -> 0.26040273 | I24: =I23/I5 -> 0.26539956 | ... K24: =K23/K5 -> 0.27119883
A26: OTHER METRICS
A27: D&A | B27: 12547 | C27: 11056 | D27: 11284 | E27: 11104 | F27: 11519 | G27: =G5*Assumptions!C10 -> 11992.988 | H27: =H5*Assumptions!D10 -> 12404.747 | I27: =I5*Assumptions!E10 -> 12935.157 | J27: =J5*Assumptions!F10 -> 13408.676 | K27: =K5*Assumptions!G10 -> 13751.342
A28: EBITDA | B28: 76477 | C28: 77344 | D28: 120233 | E28: 130541 | F28: 125820 | G28: =G16+G27 -> 131922.86 | H28: =H16+H27 -> 143723.96 | I28: =I16+I27 -> 157531.73 | J28: =J16+J27 -> 171333.08 | K28: =K16+K27 -> 182998.63
A29: EBITDA Margin % | B29: =B28/B5 -> 0.29394559 | C29: =C28/C5 -> 0.28174781 | D29: =D28/D5 -> 0.3286698 | E29: =E28/E5 -> 0.33104674 | F29: =F28/F5 -> 0.32826748 | G29: =G28/G5 -> 0.33 | H29: =H28/H5 -> 0.336 | I29: =I28/I5 -> 0.341 | ... K29: =K28/K5 -> 0.346
A30: EPS (Diluted) | B30: 3.5785247 | C30: 3.7180882 | D30: 6.1317272 | E30: 6.4635062 | F30: 6.2816527 | G30: =G23/15441 -> 6.5904569 | H30: =H23/15441 -> 7.2137322 | I30: =I23/15441 -> 7.940328 | J30: =J23/15441 -> 8.669686 | K30: =K23/15441 -> 9.2893244

Sheet Balance Sheet
A1: Balance Sheet — Apple Inc. (AAPL) | $ in Millions
B2: FY2019 | C2: FY2020 | D2: FY2021 | E2: FY2022 | F2: FY2023 | G2: FY2024E | H2: FY2025E | I2: FY2026E | J2: FY2027E | K2: FY2028E
A3: ASSETS
A4: Current Assets | G4: =F4*1.03 -> 0 | H4: =G4*1.03 -> 0 | I4: =H4*1.03 -> 0 | J4: =I4*1.03 -> 0 | K4: =J4*1.03 -> 0
A5: Cash & Equivalents | B5: 48844 | C5: 38016 | D5: 62639 | E5: 23646 | F5: 29965 | G5: =F5+'Cash Flow'!G10 -> 29965 | H5: =G5+'Cash Flow'!H10 -> 29965 | I5: =H5+'Cash Flow'!I10 -> 29965 | J5: =I5+'Cash Flow'!J10 -> 29965 | K5: =J5+'Cash Flow'!K10 -> 29965
A6: Short-Term Investments | B6: 51713 | C6: 52927 | D6: 27699 | E6: 24658 | F6: 31590 | G6: =F6*1.04 -> 32853.6 | H6: =G6*1.04 -> 34167.744 | I6: =H6*1.04 -> 35534.454 | J6: =I6*1.04 -> 36955.832 | K6: =J6*1.04 -> 38434.065
A7: Accounts Receivable | B7: 22926 | C7: 16120 | D7: 26278 | E7: 28184 | F7: 29508 | G7: ='Income Statement'!G5*0.075 -> 29982.469 | H7: ='Income Statement'!H5*0.075 -> 32081.242 | I7: ='Income Statement'!I5*0.075 -> 34647.741 | J7: ='Income Statement'!J5*0.075 -> 37246.322 | K7: ='Income Statement'!K5*0.075 -> 39667.333
A8: Inventories | B8: 4106 | C8: 4061 | D8: 6580 | E8: 4946 | F8: 6331 | G8: ='Income Statement'!G5*0.018 -> 7195.7926 | H8: ='Income Statement'!H5*0.018 -> 7699.4981 | I8: ='Income Statement'!I5*0.018 -> 8315.4579 | J8: ='Income Statement'!J5*0.018 -> 8939.1173 | K8: ='Income Statement'!K5*0.018 -> 9520.1599
A9: Other Current Assets | B9: 12352 | C9: 11264 | D9: 14111 | E9: 21223 | F9: 14695 | G9: =F9*1.04 -> 15282.8 | H9: =G9*1.04 -> 15894.112 | I9: =H9*1.04 -> 16529.876 | J9: =I9*1.04 -> 17191.072 | K9: =J9*1.04 -> 17878.714
A10: Total Current Assets | B10: 162819 | C10: 143713 | D10: 134836 | E10: 135405 | F10: 143566 | G10: =F10*1.03 -> 147872.98 | H10: =G10*1.03 -> 152309.17 | I10: =H10*1.03 -> 156878.44 | J10: =I10*1.03 -> 161584.8 | K10: =J10*1.03 -> 166432.34
A11: PP&E (Net) | B11: 37378 | C11: 36766 | D11: 39440 | E11: 42117 | F11: 43715 | G11: =F11+'Income Statement'!G27-'Income Statement'!G5*Assumptions!C12 -> 55707.988 | H11: =G11+'Income Statement'!H27-'Income Statement'!H5*Assumptions!D12 -> 68112.735 | I11: =H11+'Income Statement'!I27-'Income Statement'!I5*Assumptions!E12 -> 81047.891 | J11: =I11+'Income Statement'!J27-'Income Statement'!J5*Assumptions!F12 -> 94456.567 | K11: =J11+'Income Statement'!K27-'Income Statement'!K5*Assumptions!G12 -> 108207.91
A12: Other Long-Term Assets | B12: 32978 | C12: 42522 | D12: 48849 | E12: 54428 | F12: 64758 | G12: =F12*1.04 -> 67348.32 | H12: =G12*1.04 -> 70042.253 | I12: =H12*1.04 -> 72843.943 | J12: =I12*1.04 -> 75757.701 | K12: =J12*1.04 -> 78788.009
A13: TOTAL ASSETS | B13: 338516 | C13: 323888 | D13: 351002 | E13: 352755 | F13: 352583 | G13: =F13*1.03 -> 363160.49 | H13: =G13*1.03 -> 374055.3 | I13: =H13*1.03 -> 385276.96 | J13: =I13*1.03 -> 396835.27 | K13: =J13*1.03 -> 408740.33
A15: LIABILITIES
A16: Accounts Payable | B16: 46236 | C16: 42296 | D16: 54763 | E16: 64115 | F16: 62611 | G16: ='Income Statement'!G5*0.075 -> 29982.469 | H16: ='Income Statement'!H5*0.075 -> 32081.242 | I16: ='Income Statement'!I5*0.075 -> 34647.741 | J16: ='Income Statement'!J5*0.075 -> 37246.322 | K16: ='Income Statement'!K5*0.075 -> 39667.333
A17: Short-Term Debt | B17: 16240 | C17: 13769 | D17: 9613 | E17: 11128 | F17: 9822 | G17: =F17 -> 9822 | H17: =G17 -> 9822 | I17: =H17 -> 9822 | J17: =I17 -> 9822 | K17: =J17 -> 9822
A18: Other Current Liabilities | B18: 37720 | C18: 42684 | D18: 47493 | E18: 60845 | F18: 58829 | G18: =F18*1.04 -> 61182.16 | H18: =G18*1.04 -> 63629.446 | I18: =H18*1.04 -> 66174.624 | J18: =I18*1.04 -> 68821.609 | K18: =J18*1.04 -> 71574.474
A19: Total Current Liabilities | B19: 105718 | C19: 105392 | D19: 125481 | E19: 153982 | F19: 145308 | G19: =F19*1.03 -> 149667.24 | H19: =G19*1.03 -> 154157.26 | I19: =H19*1.03 -> 158781.97 | J19: =I19*1.03 -> 163545.43 | K19: =J19*1.03 -> 168451.8
A20: Long-Term Debt | B20: 91807 | C20: 98667 | D20: 109106 | E20: 98959 | F20: 95281 | G20: =F20 -> 95281 | H20: =G20 -> 95281 | I20: =H20 -> 95281 | J20: =I20 -> 95281 | K20: =J20 -> 95281
A21: Total Liabilities | G21: =F21*1.03 -> 0 | H21: =G21*1.03 -> 0 | I21: =H21*1.03 -> 0 | J21: =I21*1.03 -> 0 | K21: =J21*1.03 -> 0
A23: EQUITY
A24: Total Equity | B24: 90488 | C24: 65339 | D24: 63090 | E24: 50672 | F24: 62146 | G24: =F24+'Income Statement'!G22*0.5 -> 71479.315 | H24: =G24+'Income Statement'!H22*0.5 -> 81695.305 | I24: =H24+'Income Statement'!I22*0.5 -> 92940.289 | J24: =I24+'Income Statement'!J22*0.5 -> 105218.18 | K24: =J24+'Income Statement'!K22*0.5 -> 118373.6
A25: TOTAL LIABILITIES & EQUITY | G25: =F25*1.03 -> 0 | H25: =G25*1.03 -> 0 | I25: =H25*1.03 -> 0 | J25: =I25*1.03 -> 0 | K25: =J25*1.03 -> 0

Sheet Cash Flow
A1: Cash Flow Statement — Apple Inc. (AAPL) | $ in Millions
B2: FY2019 | C2: FY2020 | D2: FY2021 | E2: FY2022 | F2: FY2023 | G2: FY2024E | H2: FY2025E | I2: FY2026E | J2: FY2027E | K2: FY2028E
A3: OPERATING ACTIVITIES
A4: Net Income | B4: 55256 | C4: 57411 | D4: 94680 | E4: 99803 | F4: 96995 | G4: ='Income Statement'!G22 -> 18666.631 | H4: ='Income Statement'!H22 -> 20431.979 | I4: ='Income Statement'!I22 -> 22489.969 | J4: ='Income Statement'!J22 -> 24555.783 | K4: ='Income Statement'!K22 -> 26310.829
A5: (+) Depreciation & Amortization | B5: 12547 | C5: 11056 | D5: 11284 | E5: 11104 | F5: 11519 | G5: ='Income Statement'!G27 -> 11992.988 | H5: ='Income Statement'!H27 -> 12404.747 | I5: ='Income Statement'!I27 -> 12935.157 | J5: ='Income Statement'!J27 -> 13408.676 | K5: ='Income Statement'!K27 -> 13751.342
A6: (+/-) Changes in Working Capital | B6: 1923 | C6: 5690 | D6: -4911 | E6: 9490 | F6: -6577 | G6: =-'Income Statement'!G5*0.005 -> -1998.8313 | H6: =-'Income Statement'!H5*0.005 -> -2138.7495 | I6: =-'Income Statement'!I5*0.005 -> -2309.8494 | J6: =-'Income Statement'!J5*0.005 -> -2483.0881 | K6: =-'Income Statement'!K5*0.005 -> -2644.4889
A7: Other Operating Items | B7: -335 | C7: 6517 | D7: 2985 | E7: 1754 | F7: 8606 | G7: =F7*1.02 -> 8778.12 | H7: =G7*1.02 -> 8953.6824 | I7: =H7*1.02 -> 9132.756 | J7: =I7*1.02 -> 9315.4112 | K7: =J7*1.02 -> 9501.7194
A8: Cash from Operations | B8: 69391 | C8: 80674 | D8: 104038 | E8: 122151 | F8: 110543 | G8: =G4+G5+G6+G7 -> 37438.907 | H8: =H4+H5+H6+H7 -> 39651.658 | I8: =I4+I5+I6+I7 -> 42248.032 | J8: =J4+J5+J6+J7 -> 44796.782 | K8: =K4+K5+K6+K7 -> 46919.402
A10: INVESTING ACTIVITIES
A11: (-) Capital Expenditures | B11: -10495 | C11: -7309 | D11: -11085 | E11: -10708 | F11: -10959 | G11: =-'Income Statement'!G5*Assumptions!C12 -> 0 | H11: =-'Income Statement'!H5*Assumptions!D12 -> 0 | I11: =-'Income Statement'!I5*Assumptions!E12 -> 0 | J11: =-'Income Statement'!J5*Assumptions!F12 -> 0 | K11: =-'Income Statement'!K5*Assumptions!G12 -> 0
A12: (-) Acquisitions & Investments | B12: -35401 | C12: -3309 | D12: -3460 | E12: -11646 | F12: 7254 | G12: =F12*0.95 -> 6891.3 | H12: =G12*0.95 -> 6546.735 | I12: =H12*0.95 -> 6219.3983 | J12: =I12*0.95 -> 5908.4283 | K12: =J12*0.95 -> 5613.0069
A13: Cash from Investing | B13: -45896 | C13: -10618 | D13: -14545 | E13: -22354 | F13: -3705 | G13: =G11+G12 -> 6891.3 | H13: =H11+H12 -> 6546.735 | I13: =I11+I12 -> 6219.3983 | J13: =J11+J12 -> 5908.4283 | K13: =K11+K12 -> 5613.0069
A15: FINANCING ACTIVITIES
A16: Debt Issuance / (Repayment) | B16: -7819 | C16: -975 | D16: -14210 | E16: -9543 | F16: -5228 | G16: =F16 -> -5228 | H16: =G16 -> -5228 | I16: =H16 -> -5228 | J16: =I16 -> -5228 | K16: =J16 -> -5228
A17: Share Repurchases | B17: -66897 | C17: -72358 | D17: -85971 | E17: -89402 | F17: -77550 | G17: =-'Income Statement'!G5*0.2 -> -79953.251 | H17: =-'Income Statement'!H5*0.2 -> -85549.979 | I17: =-'Income Statement'!I5*0.2 -> -92393.977 | J17: =-'Income Statement'!J5*0.2 -> -99323.525 | K17: =-'Income Statement'!K5*0.2 -> -105779.55
A18: Dividends Paid | B18: -14119 | C18: -14081 | D18: -14467 | E18: -14841 | F18: -15025 | G18: =F18*1.04 -> -15626 | H18: =G18*1.04 -> -16251.04 | I18: =H18*1.04 -> -16901.082 | J18: =I18*1.04 -> -17577.125 | K18: =J18*1.04 -> -18280.21
A19: Cash from Financing | B19: -90976 | C19: -86820 | D19: -93353 | E19: -110749 | F19: -108488 | G19: =G16+G17+G18 -> -100807.25 | H19: =H16+H17+H18 -> -107029.02 | I19: =I16+I17+I18 -> -114523.06 | J19: =J16+J17+J18 -> -122128.65 | K19: =K16+K17+K18 -> -129287.76
A21: FREE CASH FLOW
A22: Free Cash Flow | B22: 58896 | C22: 73365 | D22: 92953 | E22: 111443 | F22: 99584 | G22: =G8+G11 -> 37438.907 | H22: =H8+H11 -> 39651.658 | I22: =I8+I11 -> 42248.032 | J22: =J8+J11 -> 44796.782 | K22: =K8+K11 -> 46919.402
A23: FCF Margin % | B23: 0.22637158 | C23: 0.26725316 | D23: 0.25409699 | E23: 0.28261498 | F23: 0.25981711 | G23: =G22/'Income Statement'!G5 -> 0.093651995 | H23: =H22/'Income Statement'!H5 -> 0.092698231 | I23: =I22/'Income Statement'!I5 -> 0.091451919 | J23: =J22/'Income Statement'!J5 -> 0.090203769 | K23: =K22/'Income Statement'!K5 -> 0.088711665
A24: YoY FCF Growth | C24: 0.24567033 | D24: 0.2669938 | E24: 0.19891773 | F24: -0.10641314 | G24: =(G22-F22)/ABS(F22) -> -0.62404696 | H24: =(H22-G22)/ABS(G22) -> 0.059102987 | I24: =(I22-H22)/ABS(H22) -> 0.065479577 | J24: =(J22-I22)/ABS(I22) -> 0.060328239 | K24: =(K22-J22)/ABS(J22) -> 0.047383322

Sheet DCF Valuation
A1: DCF Valuation — Apple Inc. (AAPL) | $ in Millions (except per share)
A3: FREE CASH FLOW PROJECTION
A4: Metric | B4: FY2024E | C4: FY2025E | D4: FY2026E | E4: FY2027E | F4: FY2028E
A5: Revenue ($M) | B5: ='Income Statement'!G5 -> 399766.26 | C5: ='Income Statement'!H5 -> 427749.89 | D5: ='Income Statement'!I5 -> 461969.88 | E5: ='Income Statement'!J5 -> 496617.63 | F5: ='Income Statement'!K5 -> 528897.77
A6: EBIT ($M) | B6: ='Income Statement'!G16 -> 119929.88 | C6: ='Income Statement'!H16 -> 131319.22 | D6: ='Income Statement'!I16 -> 144596.57 | E6: ='Income Statement'!J16 -> 157924.4 | F6: ='Income Statement'!K16 -> 169247.29
A7: (-) Taxes on EBIT | B7: =-B6*Assumptions!C9 -> -18589.131 | C7: =-C6*Assumptions!D9 -> -20354.479 | D7: =-D6*Assumptions!E9 -> -22412.469 | E7: =-E6*Assumptions!F9 -> -24478.283 | F7: =-F6*Assumptions!G9 -> -26233.329
A8: (+) D&A ($M) | B8: ='Income Statement'!G27 -> 11992.988 | C8: ='Income Statement'!H27 -> 12404.747 | D8: ='Income Statement'!I27 -> 12935.157 | E8: ='Income Statement'!J27 -> 13408.676 | F8: ='Income Statement'!K27 -> 13751.342
A9: (-) CapEx ($M) | B9: ='Cash Flow'!G11 -> 0 | C9: ='Cash Flow'!H11 -> 0 | D9: ='Cash Flow'!I11 -> 0 | E9: ='Cash Flow'!J11 -> 0 | F9: ='Cash Flow'!K11 -> 0
A10: (-) Change in NWC ($M) | B10: ='Cash Flow'!G6 -> -1998.8313 | C10: ='Cash Flow'!H6 -> -2138.7495 | D10: ='Cash Flow'!I6 -> -2309.8494 | E10: ='Cash Flow'!J6 -> -2483.0881 | F10: ='Cash Flow'!K6 -> -2644.4889
A11: Unlevered Free Cash Flow (UFCF) | B11: =B6+B7+B8+B9+B10 -> 111334.9 | C11: =C6+C7+C8+C9+C10 -> 121230.74 | D11: =D6+D7+D8+D9+D10 -> 132809.41 | E11: =E6+E7+E8+E9+E10 -> 144371.71 | F11: =F6+F7+F8+F9+F10 -> 154120.81
A12: YoY UFCF Growth | B12: "-" | C12: =(C11-B11)/ABS(B11) -> 0.088883483 | D12: =(D11-C11)/ABS(C11) -> 0.095509412 | E12: =(E11-D11)/ABS(D11) -> 0.087059325 | F12: =(F11-E11)/ABS(E11) -> 0.067527777
A15: DISCOUNT RATE & PV OF FCFs
A16: WACC | B16: =Assumptions!C33 -> 0.1055948
A17: Discount Period | B17: 1 | C17: 2 | D17: 3 | E17: 4 | F17: 5
A18: Discount Factor | B18: =1/(1+$B$16)^B17 -> 0.90449051 | C18: =1/(1+$B$16)^C17 -> 0.81810308 | D18: =1/(1+$B$16)^D17 -> 0.73996646 | E18: =1/(1+$B$16)^E17 -> 0.66929264 | F18: =1/(1+$B$16)^F17 -> 0.60536884
A19: Present Value of UFCF | B19: =B18*B11 -> 100701.36 | C19: =C18*C11 -> 99179.238 | D19: =D18*D11 -> 98274.511 | E19: =E18*E11 -> 96626.923 | F19: =F18*F11 -> 93299.936
A21: Sum of PV (FCF) | B21: =SUM(B19:F19) -> 488081.97
A24: TERMINAL VALUE
A25: Terminal Growth Rate (Gordon) | B25: 0.03
A26: Terminal Year UFCF | B26: =F11 -> 154120.81
A27: TV (Gordon Growth Model) | B27: =B26*(1+B25)/(B16-B25) -> 2099938.6
A29: Exit EBITDA Multiple | B29: 22
A30: Terminal Year EBITDA | B30: ='Income Statement'!K28 -> 182998.63
A31: TV (Exit Multiple Method) | B31: =B29*B30 -> 4025969.8
A33: Blended Terminal Value (avg) | B33: =AVERAGE(B27,B31) -> 3062954.2
A34: PV of Terminal Value | B34: =B33/(1+B16)^5 -> 1854217
A35: TV as % of Total EV | B35: =B34/(B21+B34) -> 0.79162269
A38: INTRINSIC VALUE SUMMARY
A39: PV of FCFs (Projection Period) | B39: =B21 -> 488081.97
A40: (+) PV of Terminal Value | B40: =B33 -> 3062954.2
A41: Enterprise Value (EV) | B41: =B39+B40 -> 3551036.2
A42: (-) Net Debt | B42: -65716
A43: Equity Value | B43: =B41+B42 -> 3485320.2
A44: Shares Outstanding (M) | B44: 15441
A45: Implied Share Price | B45: =B43/B44 -> 225.71855
A46: Current Share Price (Reference) | B46: 195
A47: Upside / (Downside) | B47: =(B45-B46)/B46 -> 0.15753104

Sheet Trading Comps
A1: Comparable Companies (Trading Comps) Analysis | Apple Inc. Peer Group
A2: Market data as of reference date | Source: Bloomberg / FactSet | $ in Billions
A3: Company | B3: Mkt Cap ($B) | C3: EV ($B) | D3: Revenue ($B) | E3: EBITDA ($B) | F3: EV/Revenue | G3: EV/EBITDA | H3: P/E | I3: Gross Margin | J3: Net Margin
A4: Apple (AAPL) | B4: 2850 | C4: 2920 | D4: 385.6 | E4: 125.8 | F4: 7.6x | G4: 23.2x | H4: 29.4x | I4: 43.8% | J4: 25.1%
A5: Microsoft (MSFT) | B5: 3100 | C5: 3150 | D5: 236.6 | E5: 103.5 | F5: 13.3x | G5: 30.4x | H5: 37.5x | I5: 69.4% | J5: 35.0%
A6: Alphabet (GOOGL) | B6: 2050 | C6: 1990 | D6: 307.4 | E6: 92 | F6: 6.5x | G6: 21.6x | H6: 27.8x | I6: 56.5% | J6: 24.0%
A7: Meta Platforms (META) | B7: 1350 | C7: 1300 | D7: 134.9 | E7: 56.3 | F7: 9.6x | G7: 23.1x | H7: 34.6x | I7: 80.7% | J7: 29.0%
A8: Samsung (005930) | B8: 380 | C8: 320 | D8: 200.7 | E8: 38.2 | F8: 1.6x | G8: 8.4x | H8: 26.1x | I8: 36.8% | J8: 7.3%
A9: Sony (SONY) | B9: 115 | C9: 140 | D9: 86.9 | E9: 9.4 | F9: 1.6x | G9: 14.9x | H9: 16.9x | I9: 28.0% | J9: 7.8%
A11: Min (ex. AAPL) | B11: =MIN(B5:B9) -> 115 | C11: =MIN(C5:C9) -> 140 | D11: =MIN(D5:D9) -> 86.9 | E11: =MIN(E5:E9) -> 9.4 | F11: 1.6x | G11: 8.4x | H11: 16.9x
A12: Mean (ex. AAPL) | B12: =AVERAGE(B5:B9) -> 1399 | C12: =AVERAGE(C5:C9) -> 1380 | D12: =AVERAGE(D5:D9) -> 193.3 | E12: =AVERAGE(E5:E9) -> 59.88 | F12: 6.5x | G12: 20.0x | H12: 27.8x
A13: Median (ex. AAPL) | B13: =MEDIAN(B5:B9) -> 1350 | C13: =MEDIAN(C5:C9) -> 1300 | D13: =MEDIAN(D5:D9) -> 200.7 | E13: =MEDIAN(E5:E9) -> 56.3 | F13: - | G13: - | H13: -
A14: Max (ex. AAPL) | B14: =MAX(B5:B9) -> 3100 | C14: =MAX(C5:C9) -> 3150 | D14: =MAX(D5:D9) -> 307.4 | E14: =MAX(E5:E9) -> 103.5 | F14: 13.3x | G14: 30.4x | H14: 37.5x
A17: IMPLIED VALUATION FROM COMPS MULTIPLES
A18: AAPL LTM Revenue ($B) | E18: 385.6
A19: AAPL LTM EBITDA ($B) | E19: 125.8
A20: Median Peer EV/Revenue | E20: 6.5x
A21: Median Peer EV/EBITDA | E21: 21.6x
A22: Implied EV from EV/Revenue ($B) | E22: 2506.4
A23: Implied EV from EV/EBITDA ($B) | E23: 2717.28
A24: (-) Net Debt ($B) | E24: -65.7
A25: Implied Equity Value — EV/Rev ($B) | E25: 2440.7
A26: Implied Equity Value — EV/EBITDA ($B) | E26: 2651.58
A27: Shares Outstanding (B) | E27: 15.441
A28: Implied Share Price — EV/Revenue | E28: 158.06619
A29: Implied Share Price — EV/EBITDA | E29: 171.72333

Sheet Sensitivity Analysis
A1: Sensitivity Analysis — WACC vs. Terminal Growth Rate | Implied Share Price
A3: DCF IMPLIED SHARE PRICE: WACC × Terminal Growth Rate
A4: WACC → TGR ↓ | B4: 0.085 | C4: 0.09 | D4: 0.095 | E4: 0.1 | F4: 0.105 | G4: 0.11 | H4: 0.115
A5: 0.015 | B5: 95.46 | C5: 89.26 | D5: 83.87 | E5: 79.15 | F5: 74.98 | G5: 71.29 | H5: 67.99
A6: 0.02 | B6: 101.26 | C6: 94.19 | D6: 88.11 | E6: 82.82 | F6: 78.19 | G6: 74.11 | H6: 70.48
A7: 0.025 | B7: 108.03 | C7: 99.89 | D7: 92.96 | E7: 86.99 | F7: 81.8 | G7: 77.26 | H7: 73.25
A8: 0.03 | B8: 116.03 | C8: 106.54 | D8: 98.55 | E8: 91.75 | F8: 85.89 | G8: 80.8 | H8: 76.34
A9: 0.035 | B9: 125.63 | C9: 114.39 | D9: 105.08 | E9: 97.24 | F9: 90.57 | G9: 84.82 | H9: 79.83
A10: 0.04 | B10: 137.37 | C10: 123.82 | D10: 112.79 | E10: 103.65 | F10: 95.96 | G10: 89.41 | H10: 83.77
A13: COLOR LEGEND (Base Case = WACC 10.0% / TGR 3.0% — highlighted with bold border)
A14: ≥ $220 | Strong Buy | C14: $170 – $220 | Buy / Outperform | E14: $130 – $170 | Hold / Market Perform | G14: < $130 | Underperform / Sell | I14: N/M — WACC ≤ TGR (invalid)
A17: EV/EBITDA EXIT MULTIPLE × WACC — Implied Share Price
A18: WACC → Mult ↓ | B18: 0.085 | C18: 0.09 | D18: 0.095 | E18: 0.1 | F18: 0.105 | G18: 0.11
A19: 16x | B19: 116.54 | C19: 114.46 | D19: 112.43 | E19: 110.46 | F19: 108.54 | G19: 106.67
A20: 18x | B20: 128 | C20: 125.65 | D20: 123.37 | E20: 121.16 | F20: 119 | G20: 116.9
A21: 20x | B21: 139.45 | C21: 136.85 | D21: 134.32 | E21: 131.85 | F21: 129.45 | G21: 127.12
A22: 22x | B22: 150.91 | C22: 148.05 | D22: 145.26 | E22: 142.55 | F22: 139.91 | G22: 137.34
A23: 24x | B23: 162.37 | C23: 159.24 | D23: 156.2 | E23: 153.25 | F23: 150.37 | G23: 147.57
A24: 26x | B24: 173.82 | C24: 170.44 | D24: 167.15 | E24: 163.94 | F24: 160.82 | G24: 157.79
A25: 28x | B25: 185.28 | C25: 181.64 | D25: 178.09 | E25: 174.64 | F25: 171.28 | G25: 168.01
